varphi/__init__.py
varphi/antlr/VarphiEvaluator.py
varphi/antlr/VarphiLexer.py
varphi/antlr/VarphiListener.py
varphi/antlr/VarphiParser.py
varphi/antlr/__init__.py
varphi/frontend/__init__.py
varphi/frontend/helpers.py
varphi/frontend/varphi.py
varphi/model/Head.py
varphi/model/TuringMachine.py
varphi/model/__init__.py
varphi/model/types.py
varphi-3.3.dist-info/LICENSE
varphi-3.3.dist-info/METADATA
varphi-3.3.dist-info/WHEEL
varphi-3.3.dist-info/entry_points.txt
varphi-3.3.dist-info/top_level.txt
varphi-3.3.dist-info/RECORD
